pretalx_vimeo/__init__.py
pretalx_vimeo/apps.py
pretalx_vimeo/forms.py
pretalx_vimeo/models.py
pretalx_vimeo/recording.py
pretalx_vimeo/signals.py
pretalx_vimeo/urls.py
pretalx_vimeo/views.py
pretalx_vimeo/locale/django.pot
pretalx_vimeo/locale/ar/LC_MESSAGES/django.mo
pretalx_vimeo/locale/ar/LC_MESSAGES/django.po
pretalx_vimeo/locale/bg/LC_MESSAGES/django.mo
pretalx_vimeo/locale/bg/LC_MESSAGES/django.po
pretalx_vimeo/locale/ca/LC_MESSAGES/django.mo
pretalx_vimeo/locale/ca/LC_MESSAGES/django.po
pretalx_vimeo/locale/cs/LC_MESSAGES/django.mo
pretalx_vimeo/locale/cs/LC_MESSAGES/django.po
pretalx_vimeo/locale/de_DE/LC_MESSAGES/django.mo
pretalx_vimeo/locale/de_DE/LC_MESSAGES/django.po
pretalx_vimeo/locale/de_Formal/LC_MESSAGES/django.mo
pretalx_vimeo/locale/de_Formal/LC_MESSAGES/django.po
pretalx_vimeo/locale/el/LC_MESSAGES/django.mo
pretalx_vimeo/locale/el/LC_MESSAGES/django.po
pretalx_vimeo/locale/es/LC_MESSAGES/django.mo
pretalx_vimeo/locale/es/LC_MESSAGES/django.po
pretalx_vimeo/locale/es_MX/LC_MESSAGES/django.mo
pretalx_vimeo/locale/es_MX/LC_MESSAGES/django.po
pretalx_vimeo/locale/fr_FR/LC_MESSAGES/django.mo
pretalx_vimeo/locale/fr_FR/LC_MESSAGES/django.po
pretalx_vimeo/locale/id/LC_MESSAGES/django.mo
pretalx_vimeo/locale/id/LC_MESSAGES/django.po
pretalx_vimeo/locale/it/LC_MESSAGES/django.mo
pretalx_vimeo/locale/it/LC_MESSAGES/django.po
pretalx_vimeo/locale/ja_JP/LC_MESSAGES/django.mo
pretalx_vimeo/locale/ja_JP/LC_MESSAGES/django.po
pretalx_vimeo/locale/ko/LC_MESSAGES/django.mo
pretalx_vimeo/locale/ko/LC_MESSAGES/django.po
pretalx_vimeo/locale/nl/LC_MESSAGES/django.mo
pretalx_vimeo/locale/nl/LC_MESSAGES/django.po
pretalx_vimeo/locale/pl/LC_MESSAGES/django.mo
pretalx_vimeo/locale/pl/LC_MESSAGES/django.po
pretalx_vimeo/locale/pt_BR/LC_MESSAGES/django.mo
pretalx_vimeo/locale/pt_BR/LC_MESSAGES/django.po
pretalx_vimeo/locale/pt_PT/LC_MESSAGES/django.mo
pretalx_vimeo/locale/pt_PT/LC_MESSAGES/django.po
pretalx_vimeo/locale/ru/LC_MESSAGES/django.mo
pretalx_vimeo-2.5.0.dist-info/licenses/LICENSE
pretalx_vimeo-2.5.0.dist-info/METADATA
pretalx_vimeo-2.5.0.dist-info/WHEEL
pretalx_vimeo-2.5.0.dist-info/entry_points.txt
pretalx_vimeo-2.5.0.dist-info/top_level.txt
pretalx_vimeo-2.5.0.dist-info/RECORD
