Metadata-Version: 2.4
Name: pretalx-vimeo
Version: 2.5.0
Summary: Static vimeo for pretalx, e.g. information, venue listings, a Code of Conduct, etc.
Author-email: Tobias Kunze <r@rixx.de>
Maintainer-email: Tobias Kunze <r@rixx.de>
License: Apache Software License
Project-URL: homepage, https://github.com/pretalx/pretalx-vimeo
Project-URL: repository, https://github.com/pretalx/pretalx-vimeo.git
Keywords: pretalx
License-File: LICENSE
Dynamic: license-file
